skyfi_modelship/__init__.py
skyfi_modelship/config.py
skyfi_modelship/handler/__init__.py
skyfi_modelship/handler/args_handler.py
skyfi_modelship/handler/fastapi_handler.py
skyfi_modelship/handler/rabbitmq_handler.py
skyfi_modelship/skyfi_app.py
skyfi_modelship/skyfi_types.py
skyfi_modelship/util/__init__.py
skyfi_modelship/util/execution.py
skyfi_modelship/util/inference_request.py
skyfi_modelship/util/model_transformer.py
skyfi_modelship/util/storage.py
skyfi_modelship-0.6.0.dist-info/LICENSE
skyfi_modelship-0.6.0.dist-info/METADATA
skyfi_modelship-0.6.0.dist-info/WHEEL
skyfi_modelship-0.6.0.dist-info/RECORD
