Metadata-Version: 2.1
Name: skyfi-modelship
Version: 0.6.0
Summary: SkyFi ModelShip - The Insights partners integration library.
License: MIT
Author: Atanas Balevski
Author-email: nasko@skyfi.com
Requires-Python: >=3.9,<3.12
Classifier: License :: OSI Approved :: MIT License
Classifier: Programming Language :: Python :: 3
Classifier: Programming Language :: Python :: 3.9
Classifier: Programming Language :: Python :: 3.10
Classifier: Programming Language :: Python :: 3.11
Requires-Dist: fastapi (>=0.110.0,<0.111.0)
Requires-Dist: geojson-pydantic (>=1.0.2,<2.0.0)
Requires-Dist: google-cloud-storage (>=2.14.0,<3.0.0)
Requires-Dist: loguru (>=0.7.2,<0.8.0)
Requires-Dist: orjson (>=3.9.15,<4.0.0)
Requires-Dist: pika (>=1.3.2,<2.0.0)
Requires-Dist: pydantic (>=2.6.3,<3.0.0)
Requires-Dist: pydantic-settings (>=2.2.1,<3.0.0)
Requires-Dist: pytest-mock (>=3.14.0,<4.0.0)
Requires-Dist: python-dotenv (>=1.0.1,<2.0.0)
Requires-Dist: shapely (>=2.0.3,<3.0.0)
Requires-Dist: simple-parsing (>=0.1.5,<0.2.0)
Requires-Dist: uvicorn[standard] (>=0.27.1,<0.28.0)
